.installed.cfg
.mr.developer.cfg
.travis.yml
MANIFEST.in
Makefile
README.rst
bootstrap.py
buildout.cfg
setup.py
buildout.d/base.cfg
buildout.d/development.cfg
buildout.d/travis.cfg
buildout.d/versions.cfg
docs/CHANGELOG.rst
docs/api.rst
docs/conf.py
docs/glossary.rst
docs/index.rst
parts/omelette/plone/app/hud/__init__.py
parts/omelette/plone/app/hud/configure.zcml
parts/omelette/plone/app/hud/hud_best_practices.pt
parts/omelette/plone/app/hud/hud_best_practices.py
parts/omelette/plone/app/hud/hud_content_browser.pt
parts/omelette/plone/app/hud/hud_content_browser.py
parts/omelette/plone/app/hud/hud_list_users.pt
parts/omelette/plone/app/hud/hud_security_advisories.pt
parts/omelette/plone/app/hud/hud_security_advisories.py
parts/omelette/plone/app/hud/hud_users.pt
parts/omelette/plone/app/hud/hud_users.py
parts/omelette/plone/app/hud/interfaces.py
parts/omelette/plone/app/hud/testing.py
parts/omelette/plone/app/hud/profiles/default/browserlayer.xml
parts/omelette/plone/app/hud/profiles/default/controlpanel.xml
parts/omelette/plone/app/hud/profiles/default/cssregistry.xml
parts/omelette/plone/app/hud/profiles/default/metadata.xml
parts/omelette/plone/app/hud/static/general.css
parts/omelette/plone/app/hud/tests/__init__.py
parts/omelette/plone/app/hud/tests/test_best_practices.py
parts/omelette/plone/app/hud/tests/test_content_browser.py
parts/omelette/plone/app/hud/tests/test_security_advisories.py
parts/omelette/plone/app/hud/tests/test_setup.py
parts/omelette/plone/app/hud/tests/test_users.py
parts/omelette/plone/app/hud/translation/locales/plone.app.hud.pot
parts/omelette/plone/app/hud/translation/locales/es/LC_MESSAGES/plone.app.hud.po
parts/omelette/plone/app/hud/translation/locales/ru/LC_MESSAGES/plone.app.hud.po
parts/omelette/plone/app/hud/translation/locales/sl/LC_MESSAGES/plone.app.hud.po
src/plone/__init__.py
src/plone/__init__.pyc
src/plone.app.hud.egg-info/PKG-INFO
src/plone.app.hud.egg-info/SOURCES.txt
src/plone.app.hud.egg-info/dependency_links.txt
src/plone.app.hud.egg-info/entry_points.txt
src/plone.app.hud.egg-info/namespace_packages.txt
src/plone.app.hud.egg-info/not-zip-safe
src/plone.app.hud.egg-info/requires.txt
src/plone.app.hud.egg-info/top_level.txt
src/plone/app/__init__.py
src/plone/app/__init__.pyc
src/plone/app/hud/__init__.py
src/plone/app/hud/__init__.pyc
