Metadata-Version: 1.1
Name: plone.app.hud
Version: 1.0a1
Summary: Plone Heads Up Display Panels
Home-page: http://pypi.python.org/pypi/plone.app.hud
Author: Plone Foundation
Author-email: plone-developers@lists.sourceforge.net
License: GPL version 2
Keywords: Plone HUD Panels
Platform: UNKNOWN
Classifier: Framework :: Plone
Classifier: Programming Language :: Python
Classifier: Development Status :: 3 - Alpha
